{"name":"Chatbot","created":"2017-05-25T04:58:07.439Z","intents":[{"intent":"Hello","created":"2017-05-25T05:00:56.356Z","updated":"2017-05-25T05:01:29.876Z","examples":[{"text":"Good Morning","created":"2017-05-25T05:01:03.667Z","updated":"2017-05-25T05:01:03.667Z"},{"text":"Good Evening","created":"2017-05-25T05:01:09.549Z","updated":"2017-05-25T05:01:09.549Z"},{"text":"Good Afternoon","created":"2017-05-25T05:01:17.864Z","updated":"2017-05-25T05:01:17.864Z"},{"text":"Hello","created":"2017-05-25T05:01:22.004Z","updated":"2017-05-25T05:01:22.004Z"},{"text":"Hi","created":"2017-05-25T05:01:28.546Z","updated":"2017-05-25T05:01:28.546Z"},{"text":"Hola","created":"2017-05-25T05:01:29.876Z","updated":"2017-05-25T05:01:29.876Z"}],"description":null},{"intent":"Hardware-Issues","created":"2017-05-25T04:59:48.525Z","updated":"2017-05-25T05:00:40.010Z","examples":[{"text":"My computer is not turning on","created":"2017-05-25T04:59:57.280Z","updated":"2017-05-25T04:59:57.280Z"},{"text":"My Hard disk is not workin","created":"2017-05-25T05:00:09.591Z","updated":"2017-05-25T05:00:09.591Z"},{"text":"My laptop is not charging","created":"2017-05-25T05:00:24.229Z","updated":"2017-05-25T05:00:24.229Z"},{"text":"My printer is not working","created":"2017-05-25T05:00:34.091Z","updated":"2017-05-25T05:00:34.091Z"},{"text":"My pc is off","created":"2017-05-25T05:00:40.010Z","updated":"2017-05-25T05:00:40.010Z"}],"description":null},{"intent":"bye","created":"2017-05-25T09:28:15.492Z","updated":"2017-05-25T09:28:48.303Z","examples":[{"text":"good bye","created":"2017-05-25T09:28:19.947Z","updated":"2017-05-25T09:28:19.947Z"},{"text":"bye","created":"2017-05-25T09:28:21.737Z","updated":"2017-05-25T09:28:21.737Z"},{"text":"thank you","created":"2017-05-25T09:28:27.799Z","updated":"2017-05-25T09:28:27.799Z"},{"text":"see you then","created":"2017-05-25T09:28:40.118Z","updated":"2017-05-25T09:28:40.118Z"},{"text":"thank you for assistance","created":"2017-05-25T09:28:48.303Z","updated":"2017-05-25T09:28:48.303Z"}],"description":null},{"intent":"Affirmative","created":"2017-05-25T05:01:41.277Z","updated":"2017-05-25T05:02:00.035Z","examples":[{"text":"correct","created":"2017-05-25T05:01:46.832Z","updated":"2017-05-25T05:01:46.832Z"},{"text":"right","created":"2017-05-25T05:01:48.379Z","updated":"2017-05-25T05:01:48.379Z"},{"text":"exaclty","created":"2017-05-25T05:01:51.454Z","updated":"2017-05-25T05:01:51.454Z"},{"text":"yes","created":"2017-05-25T05:01:56.069Z","updated":"2017-05-25T05:01:56.069Z"},{"text":"yeap","created":"2017-05-25T05:01:58.108Z","updated":"2017-05-25T05:01:58.108Z"},{"text":"you are right","created":"2017-05-25T05:02:00.035Z","updated":"2017-05-25T05:02:00.035Z"}],"description":null},{"intent":"Software-issues","created":"2017-05-25T04:58:23.918Z","updated":"2017-05-25T05:24:29.821Z","examples":[{"text":"Application Issue","created":"2017-05-25T04:58:36.811Z","updated":"2017-05-25T04:58:36.811Z"},{"text":"Issues with Offcice","created":"2017-05-25T04:58:41.936Z","updated":"2017-05-25T04:58:41.936Z"},{"text":"Problems with automatic updates","created":"2017-05-25T04:58:56.379Z","updated":"2017-05-25T04:58:56.379Z"},{"text":"My email is not working","created":"2017-05-25T04:59:08.468Z","updated":"2017-05-25T04:59:08.468Z"},{"text":"Application not running","created":"2017-05-25T04:59:16.446Z","updated":"2017-05-25T04:59:16.446Z"},{"text":"Windows not booting","created":"2017-05-25T05:24:29.821Z","updated":"2017-05-25T05:24:29.821Z"}],"description":null}],"updated":"2017-05-25T09:39:00.016Z","entities":[{"entity":"Security","values":[{"value":"Privacy","created":"2017-05-25T05:05:51.645Z","updated":"2017-05-25T05:05:51.645Z","metadata":null,"synonyms":[]},{"value":"Data Loss","created":"2017-05-25T05:05:47.773Z","updated":"2017-05-25T05:05:47.773Z","metadata":null,"synonyms":[]},{"value":"Spyware","created":"2017-05-25T05:05:57.108Z","updated":"2017-05-25T05:05:57.108Z","metadata":null,"synonyms":[]},{"value":"SPAM","created":"2017-05-25T05:05:54.170Z","updated":"2017-05-25T05:05:54.170Z","metadata":null,"synonyms":[]},{"value":"Virus","created":"2017-05-25T05:06:00.093Z","updated":"2017-05-25T05:06:00.093Z","metadata":null,"synonyms":[]}],"created":"2017-05-25T05:05:42.345Z","updated":"2017-05-25T05:06:00.093Z","metadata":null,"description":null},{"entity":"Printers","values":[{"value":"Colorjet","created":"2017-05-25T05:07:01.562Z","updated":"2017-05-25T05:07:01.562Z","metadata":null,"synonyms":[]},{"value":"Laserjet","created":"2017-05-25T05:07:15.956Z","updated":"2017-05-25T05:07:15.956Z","metadata":null,"synonyms":[]},{"value":"Color stylus","created":"2017-05-25T05:07:07.966Z","updated":"2017-05-25T05:07:07.966Z","metadata":null,"synonyms":[]},{"value":"Full color","created":"2017-05-25T05:07:19.720Z","updated":"2017-05-25T05:07:22.735Z","metadata":null,"synonyms":[]},{"value":"Inkjet","created":"2017-05-25T05:07:12.398Z","updated":"2017-05-25T05:07:12.398Z","metadata":null,"synonyms":[]}],"created":"2017-05-25T05:06:54.786Z","updated":"2017-05-25T05:07:22.735Z","metadata":null,"description":null},{"entity":"OS","values":[{"value":"Red Hat","created":"2017-05-25T05:06:28.484Z","updated":"2017-05-25T05:06:28.484Z","metadata":null,"synonyms":[]},{"value":"Windows","created":"2017-05-25T05:06:35.669Z","updated":"2017-05-25T05:06:35.669Z","metadata":null,"synonyms":[]},{"value":"UNIX","created":"2017-05-25T05:06:38.335Z","updated":"2017-05-25T05:06:38.335Z","metadata":null,"synonyms":[]},{"value":"HPUX","created":"2017-05-25T05:06:23.668Z","updated":"2017-05-25T05:06:23.668Z","metadata":null,"synonyms":[]},{"value":"Linux","created":"2017-05-25T05:06:31.691Z","updated":"2017-05-25T05:06:31.691Z","metadata":null,"synonyms":[]}],"created":"2017-05-25T05:06:15.094Z","updated":"2017-05-25T05:06:38.335Z","metadata":null,"description":null},{"entity":"Brands","values":[{"value":"Acer","created":"2017-05-25T05:07:39.621Z","updated":"2017-05-25T05:07:39.621Z","metadata":null,"synonyms":[]},{"value":"Lenovo","created":"2017-05-25T05:07:57.931Z","updated":"2017-05-25T05:07:57.931Z","metadata":null,"synonyms":[]},{"value":"Asus","created":"2017-05-25T05:07:44.091Z","updated":"2017-05-25T05:07:44.091Z","metadata":null,"synonyms":[]},{"value":"Toshiba","created":"2017-05-25T05:07:50.992Z","updated":"2017-05-25T05:07:50.992Z","metadata":null,"synonyms":[]},{"value":"Apple","created":"2017-05-25T05:07:53.415Z","updated":"2017-05-25T05:07:53.415Z","metadata":null,"synonyms":[]},{"value":"HP","created":"2017-05-25T05:07:47.239Z","updated":"2017-05-25T05:07:47.239Z","metadata":null,"synonyms":[]}],"created":"2017-05-25T05:07:35.050Z","updated":"2017-05-25T05:07:57.931Z","metadata":null,"description":null}],"language":"en","metadata":null,"description":"Chatbot","dialog_nodes":[{"go_to":null,"output":{},"parent":"Affirmative HW","context":null,"created":"2017-05-25T05:11:56.913Z","updated":"2017-05-25T09:38:56.018Z","metadata":null,"conditions":"@Brands","description":null,"dialog_node":"HW Brands","previous_sibling":null},{"go_to":null,"output":{},"parent":"Affirmative-SW","context":null,"created":"2017-05-25T05:20:51.030Z","updated":"2017-05-25T09:39:00.016Z","metadata":null,"conditions":"@OS","description":null,"dialog_node":"OS","previous_sibling":null},{"go_to":null,"output":{"text":{"values":["Got it can you tell me the OS you are using?"],"selection_policy":"sequential"}},"parent":"Software Issues","context":null,"created":"2017-05-25T05:19:47.560Z","updated":"2017-05-25T05:20:32.606Z","metadata":null,"conditions":"#Affirmative","description":null,"dialog_node":"Affirmative-SW","previous_sibling":null},{"go_to":null,"output":{"text":{"values":["Got it, Please tell me the brand"],"selection_policy":"sequential"}},"parent":"Hardware Issues","context":null,"created":"2017-05-25T05:11:05.747Z","updated":"2017-05-25T09:37:05.562Z","metadata":null,"conditions":"#Affirmative","description":null,"dialog_node":"Affirmative HW","previous_sibling":null},{"go_to":null,"output":{"text":{"values":["Looks like you have software issue"],"selection_policy":"sequential"}},"parent":null,"context":null,"created":"2017-05-25T05:18:46.216Z","updated":"2017-05-25T05:19:36.486Z","metadata":null,"conditions":"#Software-issues","description":null,"dialog_node":"Software Issues","previous_sibling":"Hardware Issues"},{"go_to":null,"output":{"text":{"values":["Looks like you having hardware issues"],"selection_policy":"sequential"}},"parent":null,"context":null,"created":"2017-05-25T05:09:54.600Z","updated":"2017-05-25T05:10:52.965Z","metadata":null,"conditions":"#Hardware-Issues","description":null,"dialog_node":"Hardware Issues","previous_sibling":"Bye"},{"go_to":null,"output":{"text":{"values":["Welcome to Service Desk"],"selection_policy":"sequential"}},"parent":null,"context":null,"created":"2017-05-25T05:08:23.893Z","updated":"2017-05-25T09:03:55.260Z","metadata":null,"conditions":"conversation_start","description":null,"dialog_node":"conversation_start","previous_sibling":null},{"go_to":null,"output":{"text":{"values":["You are welcome!!"],"selection_policy":"sequential"}},"parent":null,"context":null,"created":"2017-05-25T09:29:25.659Z","updated":"2017-05-25T09:36:28.331Z","metadata":null,"conditions":"#bye","description":null,"dialog_node":"Bye","previous_sibling":"Hello"},{"go_to":null,"output":{"text":{"values":["Hello.I am watson,  How can I help you?","Please let me know How I can help you?"],"selection_policy":"sequential"}},"parent":null,"context":null,"created":"2017-05-25T09:02:41.792Z","updated":"2017-05-25T09:05:01.887Z","metadata":null,"conditions":"#Hello","description":null,"dialog_node":"Hello","previous_sibling":"conversation_start"},{"go_to":null,"output":{"text":{"values":["I didn't understand. You can try rephrasing.","Can you reword your statement? I'm not understanding.","I didn't get your meaning."],"selection_policy":"sequential"}},"parent":null,"context":null,"created":"2017-05-25T05:08:23.893Z","updated":"2017-05-25T09:30:20.853Z","metadata":null,"conditions":"anything_else || #Affirmative","description":null,"dialog_node":"Anything else","previous_sibling":"Software Issues"},{"type":"response_condition","go_to":null,"output":{"text":{"values":["For support with Acer Hardware, Please go to the following shop"],"selection_policy":"sequential"}},"parent":"HW Brands","context":null,"created":"2017-05-25T05:12:45.932Z","updated":"2017-05-25T05:14:37.871Z","metadata":null,"conditions":" @Brands:Acer","description":null,"dialog_node":"node_6_1495689162786","previous_sibling":null},{"type":"response_condition","go_to":null,"output":{"text":{"values":["For support with Asus Hardware, Please go to the following shop"],"selection_policy":"sequential"}},"parent":"HW Brands","context":null,"created":"2017-05-25T05:14:41.139Z","updated":"2017-05-25T05:14:57.717Z","metadata":null,"conditions":" @Brands:Asus","description":null,"dialog_node":"node_8_1495689279211","previous_sibling":"node_7_1495689216798"},{"type":"response_condition","go_to":null,"output":{"text":{"values":["For windows issue, Please visit the following page"],"selection_policy":"sequential"}},"parent":"OS","context":null,"created":"2017-05-25T05:21:16.152Z","updated":"2017-05-25T05:22:38.940Z","metadata":null,"conditions":"@OS:Windows","description":null,"dialog_node":"node_16_1495689674127","previous_sibling":null},{"type":"response_condition","go_to":null,"output":{"text":{"values":["Sorry For Red hat . There is no support"],"selection_policy":"sequential"}},"parent":"OS","context":null,"created":"2017-05-25T05:22:40.491Z","updated":"2017-05-25T05:23:10.060Z","metadata":null,"conditions":" @OS:(Red Hat)","description":null,"dialog_node":"node_17_1495689758496","previous_sibling":"node_16_1495689674127"},{"type":"response_condition","go_to":null,"output":{"text":{"values":["We do not provide support for Apple Devices. Please visit Apple store"],"selection_policy":"sequential"}},"parent":"HW Brands","context":null,"created":"2017-05-25T05:13:39.721Z","updated":"2017-05-25T09:33:27.592Z","metadata":null,"conditions":" @Brands:Apple","description":null,"dialog_node":"node_7_1495689216798","previous_sibling":"node_6_1495689162786"}],"workspace_id":"9077a6a6-ecf8-467b-9e9b-c77df67be799","counterexamples":[]}